{
    "Ar36": {
        "error": 0.0031775092867571985,
        "error_type": null,
        "filter_outliers_dict": {
            "filter_outliers": false,
            "iterations": 1,
            "std_devs": 2
        },
        "fit": "linear",
        "value": 2.7298482314395445
    },
    "Ar36L2": {
        "error": 0.007048096894954507,
        "error_type": null,
        "filter_outliers_dict": {
            "filter_outliers": false,
            "iterations": 1,
            "std_devs": 2
        },
        "fit": "linear",
        "value": 2.7365469494715473
    },
    "Ar37": {
        "error": 0.006815522236617843,
        "error_type": null,
        "filter_outliers_dict": {
            "filter_outliers": false,
            "iterations": 1,
            "std_devs": 2
        },
        "fit": "linear",
        "value": 0.024946312125188774
    },
    "Ar37L1": {
        "error": 0.017222267439305033,
        "error_type": null,
        "filter_outliers_dict": {
            "filter_outliers": false,
            "iterations": 1,
            "std_devs": 2
        },
        "fit": "linear",
        "value": 0.023777656366843324
    },
    "Ar38": {
        "error": 0.01539084302095016,
        "error_type": null,
        "filter_outliers_dict": {
            "filter_outliers": false,
            "iterations": 1,
            "std_devs": 2
        },
        "fit": "linear",
        "value": 0.4987829873317376
    },
    "Ar38AX": {
        "error": 0.00861539907104478,
        "error_type": null,
        "filter_outliers_dict": {
            "filter_outliers": false,
            "iterations": 1,
            "std_devs": 2
        },
        "fit": "linear",
        "value": 0.4859077705866421
    },
    "Ar39": {
        "error": 0.007629198105649173,
        "error_type": null,
        "filter_outliers_dict": {
            "filter_outliers": false,
            "iterations": 1,
            "std_devs": 2
        },
        "fit": "linear",
        "value": 0.02816420611739726
    },
    "Ar39H1": {
        "error": 0.01663033466864615,
        "error_type": null,
        "filter_outliers_dict": {
            "filter_outliers": false,
            "iterations": 1,
            "std_devs": 2
        },
        "fit": "linear",
        "value": -0.07574815444967781
    },
    "Ar40": {
        "error": 0.06781915049095721,
        "error_type": null,
        "filter_outliers_dict": {
            "filter_outliers": false,
            "iterations": 1,
            "std_devs": 2
        },
        "fit": "parabolic",
        "value": 824.1624496633372
    },
    "Ar40H2": {
        "error": 0.06554499064401388,
        "error_type": null,
        "filter_outliers_dict": {
            "filter_outliers": false,
            "iterations": 1,
            "std_devs": 2
        },
        "fit": "parabolic",
        "value": 823.9578852333036
    },
    "Ar41": {
        "error": 0.0,
        "error_type": null,
        "filter_outliers_dict": {
            "filter_outliers": false,
            "iterations": 1,
            "std_devs": 2
        },
        "fit": "linear",
        "value": 0.0
    }
}