{
    "Ar36": {
        "error": 0.003420453184084199,
        "error_type": null,
        "filter_outliers_dict": {
            "filter_outliers": false,
            "iterations": 1,
            "std_devs": 2
        },
        "fit": "linear",
        "value": 2.75731712627781
    },
    "Ar36L2": {
        "error": 0.007335234243382131,
        "error_type": null,
        "filter_outliers_dict": {
            "filter_outliers": false,
            "iterations": 1,
            "std_devs": 2
        },
        "fit": "linear",
        "value": 2.7662532770585626
    },
    "Ar37": {
        "error": 0.007234716884475725,
        "error_type": null,
        "filter_outliers_dict": {
            "filter_outliers": false,
            "iterations": 1,
            "std_devs": 2
        },
        "fit": "linear",
        "value": 0.04112888830091639
    },
    "Ar37L1": {
        "error": 0.016093031800360962,
        "error_type": null,
        "filter_outliers_dict": {
            "filter_outliers": false,
            "iterations": 1,
            "std_devs": 2
        },
        "fit": "linear",
        "value": -0.018185026836045348
    },
    "Ar38": {
        "error": 0.016959943845623562,
        "error_type": null,
        "filter_outliers_dict": {
            "filter_outliers": false,
            "iterations": 1,
            "std_devs": 2
        },
        "fit": "linear",
        "value": 0.48189315329538396
    },
    "Ar38AX": {
        "error": 0.007756755756108689,
        "error_type": null,
        "filter_outliers_dict": {
            "filter_outliers": false,
            "iterations": 1,
            "std_devs": 2
        },
        "fit": "linear",
        "value": 0.5215927054774048
    },
    "Ar39": {
        "error": 0.00811515636702521,
        "error_type": null,
        "filter_outliers_dict": {
            "filter_outliers": false,
            "iterations": 1,
            "std_devs": 2
        },
        "fit": "linear",
        "value": 0.045578201745496316
    },
    "Ar39H1": {
        "error": 0.01446039440511492,
        "error_type": null,
        "filter_outliers_dict": {
            "filter_outliers": false,
            "iterations": 1,
            "std_devs": 2
        },
        "fit": "linear",
        "value": -0.048835767976448945
    },
    "Ar40": {
        "error": 0.07634109826831839,
        "error_type": null,
        "filter_outliers_dict": {
            "filter_outliers": false,
            "iterations": 1,
            "std_devs": 2
        },
        "fit": "parabolic",
        "value": 821.0273910437525
    },
    "Ar40H2": {
        "error": 0.06379837632726909,
        "error_type": null,
        "filter_outliers_dict": {
            "filter_outliers": false,
            "iterations": 1,
            "std_devs": 2
        },
        "fit": "parabolic",
        "value": 820.4441438247252
    },
    "Ar41": {
        "error": 0.0,
        "error_type": null,
        "filter_outliers_dict": {
            "filter_outliers": false,
            "iterations": 1,
            "std_devs": 2
        },
        "fit": "linear",
        "value": 0.0
    }
}